simplegcd/Deployer.py
simplegcd/__init__.py
simplegcd-1.1.0.dist-info/LICENCE
simplegcd-1.1.0.dist-info/METADATA
simplegcd-1.1.0.dist-info/WHEEL
simplegcd-1.1.0.dist-info/top_level.txt
simplegcd-1.1.0.dist-info/RECORD
