Metadata-Version: 2.1
Name: simplegcd
Version: 1.1.0
Summary: A package for simple deployment of Google cloud instance groups
Author: Cabe Towers
Author-email: <cabe.towers@gmail.com>
Keywords: python,google-cloud,google-cloud-compute
Classifier: Intended Audience :: Developers
Classifier: Programming Language :: Python :: 3
Classifier: Operating System :: Unix
Classifier: Operating System :: MacOS :: MacOS X
Classifier: Operating System :: Microsoft :: Windows
License-File: LICENCE
Requires-Dist: google-cloud-compute
